README.md
setup.cfg
setup.py
test/test_check_result.py
test/test_date_statistics.py
test/test_date_window.py
test/test_inline_response400.py
test/test_inline_response400_validations.py
test/test_inline_response401.py
test/test_inline_response403.py
test/test_inline_response415.py
test/test_inline_response429.py
test/test_inline_response500.py
test/test_inline_response501.py
test/test_inline_response502.py
test/test_inline_response503.py
test/test_inline_response504.py
test/test_inline_response_default.py
test/test_method_name.py
test/test_method_statistics.py
test/test_reports_api.py
test/test_service_name.py
test/test_service_statistics.py
test/test_statistics_api.py
test/test_system_api.py
test/test_trace_data.py
test/test_user_report_filter.py
test/test_user_statistics.py
test/test_user_statistics_filter.py
test/test_version_result.py
vrt_lss_partner/__init__.py
vrt_lss_partner/api_client.py
vrt_lss_partner/configuration.py
vrt_lss_partner/exceptions.py
vrt_lss_partner/model_utils.py
vrt_lss_partner/rest.py
vrt_lss_partner.egg-info/PKG-INFO
vrt_lss_partner.egg-info/SOURCES.txt
vrt_lss_partner.egg-info/dependency_links.txt
vrt_lss_partner.egg-info/requires.txt
vrt_lss_partner.egg-info/top_level.txt
vrt_lss_partner/api/__init__.py
vrt_lss_partner/api/reports_api.py
vrt_lss_partner/api/statistics_api.py
vrt_lss_partner/api/system_api.py
vrt_lss_partner/apis/__init__.py
vrt_lss_partner/model/__init__.py
vrt_lss_partner/model/check_result.py
vrt_lss_partner/model/date_statistics.py
vrt_lss_partner/model/date_window.py
vrt_lss_partner/model/inline_response400.py
vrt_lss_partner/model/inline_response400_validations.py
vrt_lss_partner/model/inline_response401.py
vrt_lss_partner/model/inline_response403.py
vrt_lss_partner/model/inline_response415.py
vrt_lss_partner/model/inline_response429.py
vrt_lss_partner/model/inline_response500.py
vrt_lss_partner/model/inline_response501.py
vrt_lss_partner/model/inline_response502.py
vrt_lss_partner/model/inline_response503.py
vrt_lss_partner/model/inline_response504.py
vrt_lss_partner/model/inline_response_default.py
vrt_lss_partner/model/method_name.py
vrt_lss_partner/model/method_statistics.py
